methodmethodwebtest/__init__.py
methodmethodwebtest/core/__init__.py
methodmethodwebtest/core/datetime_utils.py
methodmethodwebtest/core/pydantic_utilities.py
methodmethodwebtest/core/serialization.py
methodmethodwebtest/py.typed
methodmethodwebtest/resources/__init__.py
methodmethodwebtest/resources/configs/__init__.py
methodmethodwebtest/resources/configs/header_buffer_overflow_config.py
methodmethodwebtest/resources/configs/header_misconfiguration_config.py
methodmethodwebtest/resources/configs/header_server_overload_config.py
methodmethodwebtest/resources/configs/header_user_agent_config.py
methodmethodwebtest/resources/configs/injection_location.py
methodmethodwebtest/resources/configs/multi_injection_config.py
methodmethodwebtest/resources/configs/path_crlf_config.py
methodmethodwebtest/resources/configs/path_mod_file_config.py
methodmethodwebtest/resources/configs/path_traversal_config.py
methodmethodwebtest/resources/configs/query_reverse_proxy_config.py
methodmethodwebtest/resources/report/__init__.py
methodmethodwebtest/resources/report/attempt_info.py
methodmethodwebtest/resources/report/engine_config.py
methodmethodwebtest/resources/report/header_misconfiguration_engine_config.py
methodmethodwebtest/resources/report/injection_engine_config.py
methodmethodwebtest/resources/report/path_traversal_engine_config.py
methodmethodwebtest/resources/report/report.py
methodmethodwebtest/resources/report/target_info.py
methodmethodwebtest/resources/request/__init__.py
methodmethodwebtest/resources/request/event_type.py
methodmethodwebtest/resources/request/header_event.py
methodmethodwebtest/resources/request/http_method.py
methodmethodwebtest/resources/request/multi_event.py
methodmethodwebtest/resources/request/path_event.py
methodmethodwebtest/resources/request/query_event.py
methodmethodwebtest/resources/request/request_info.py
methodmethodwebtest/resources/request/request_params.py
methodmethodwebtest-0.0.1.dist-info/METADATA
methodmethodwebtest-0.0.1.dist-info/WHEEL
methodmethodwebtest-0.0.1.dist-info/RECORD
